[
  {
    "costs": [
      72278072.51094893,
      69868453.61485577
    ],
    "dataset_name": "IMC-gate",
    "formulation": "gtsam",
    "init_file": "rank3_init10.txt",
    "times": [
      17.763846571,
      16.733313589
    ]
  },
  {
    "costs": [
      72965207.0967474,
      71715683.45126942
    ],
    "dataset_name": "IMC-gate",
    "formulation": "gtsam",
    "init_file": "rank3_init1.txt",
    "times": [
      16.878081883,
      16.734660477
    ]
  },
  {
    "costs": [
      73046723.58486973,
      72043826.44023398
    ],
    "dataset_name": "IMC-gate",
    "formulation": "gtsam",
    "init_file": "rank3_init2.txt",
    "times": [
      16.939416084,
      16.480000175
    ]
  },
  {
    "costs": [
      73078514.63035925,
      72005729.59667297
    ],
    "dataset_name": "IMC-gate",
    "formulation": "gtsam",
    "init_file": "rank3_init3.txt",
    "times": [
      17.220950573,
      16.665831507
    ]
  },
  {
    "costs": [
      72642795.8077457,
      70927548.96793006
    ],
    "dataset_name": "IMC-gate",
    "formulation": "gtsam",
    "init_file": "rank3_init4.txt",
    "times": [
      16.645646542,
      16.541409995
    ]
  },
  {
    "costs": [
      72942170.2640024,
      71807764.43324684
    ],
    "dataset_name": "IMC-gate",
    "formulation": "gtsam",
    "init_file": "rank3_init5.txt",
    "times": [
      16.671651965,
      16.813960699
    ]
  },
  {
    "costs": [
      72612897.33206223,
      70987824.66637188
    ],
    "dataset_name": "IMC-gate",
    "formulation": "gtsam",
    "init_file": "rank3_init6.txt",
    "times": [
      17.305954444,
      16.809539519
    ]
  },
  {
    "costs": [
      72493878.67861581,
      70729366.8983438
    ],
    "dataset_name": "IMC-gate",
    "formulation": "gtsam",
    "init_file": "rank3_init7.txt",
    "times": [
      16.932786393,
      16.726286855
    ]
  },
  {
    "costs": [
      72623766.34218377,
      70782420.45862861
    ],
    "dataset_name": "IMC-gate",
    "formulation": "gtsam",
    "init_file": "rank3_init8.txt",
    "times": [
      16.778017628,
      16.59485853
    ]
  },
  {
    "costs": [
      73089614.44572169,
      72214820.88087386
    ],
    "dataset_name": "IMC-gate",
    "formulation": "gtsam",
    "init_file": "rank3_init9.txt",
    "times": [
      17.073146059,
      16.43215931
    ]
  }
]
